_dlib_pybind11.cpython-37m-x86_64-linux-gnu.so
dlib/__init__.py
hmcsdlib_gpu-19.22.99.dist-info/LICENSE.txt
hmcsdlib_gpu-19.22.99.dist-info/METADATA
hmcsdlib_gpu-19.22.99.dist-info/WHEEL
hmcsdlib_gpu-19.22.99.dist-info/top_level.txt
hmcsdlib_gpu-19.22.99.dist-info/RECORD
